{
  "clientId": "CLT-01456",
  "emailAccount": "account-015",
  "basicInfo": {
    "name": "Linda Hill",
    "email": "linda.hill@company.fr",
    "company": "Whimsical Johnson Toys & Games",
    "website": "www.whimsicaljohnsontoysgames.fr",
    "country": "FR",
    "countryName": "France",
    "timezone": "Europe/Paris",
    "language": "fr",
    "phone": "+8048026598403",
    "position": "Director",
    "linkedIn": ""
  },
  "businessProfile": {
    "clientLevel": "A",
    "industry": "Distributor",
    "purchaseCategory": [
      "classic-toys"
    ],
    "estimatedVolume": "large",
    "companySize": "51-200",
    "annualRevenue": "$50M+",
    "firstContactExhibition": "Australian Toy Association Fair",
    "firstContactYear": 2026,
    "lastContactDate": "2026-04-05",
    "status": "churned",
    "preferredContactTime": "10:00",
    "notes": ""
  },
  "communicationHistory": {
    "totalEmailsSent": 3,
    "totalRepliesReceived": 1,
    "lastReplyDate": null,
    "replyRate": 33,
    "lastReplyIntent": null
  },
  "aiInsights": {
    "bestSendingDay": "Tuesday",
    "optimalTime": "15:00",
    "responsePattern": null,
    "interestProducts": [
      "classic-toys"
    ],
    "stylePreference": "formal",
    "lastDistillMatchScore": 0,
    "engagementScore": 34,
    "priorityScore": 97
  },
  "tags": [],
  "metadata": {
    "createdAt": "2022-12-17T14:32:52.152Z",
    "updatedAt": "2026-05-09T14:32:52.152Z",
    "version": 1,
    "dataHash": "e51c61bd9d7edf81",
    "importSource": "system-initialization",
    "importBatch": "batch-001-2026-05-09"
  }
}