{
  "clientId": "CLT-07261",
  "emailAccount": "account-073",
  "basicInfo": {
    "name": "Jessica Sanchez",
    "email": "jessica.sanchez@company.co.uk",
    "company": "Ultra Martin Kids World",
    "website": "www.ultramartinkidsworld.co.uk",
    "country": "GB",
    "countryName": "United Kingdom",
    "timezone": "Europe/London",
    "language": "en",
    "phone": "+97364342555",
    "position": "CEO",
    "linkedIn": ""
  },
  "businessProfile": {
    "clientLevel": "C",
    "industry": "Distributor",
    "purchaseCategory": [
      "smart-toys"
    ],
    "estimatedVolume": "small",
    "companySize": "51-200",
    "annualRevenue": "$50M+",
    "firstContactExhibition": "New York Toy Fair",
    "firstContactYear": 2015,
    "lastContactDate": "2024-05-21",
    "status": "sleeping",
    "preferredContactTime": "10:00",
    "notes": ""
  },
  "communicationHistory": {
    "totalEmailsSent": 10,
    "totalRepliesReceived": 0,
    "lastReplyDate": null,
    "replyRate": 0,
    "lastReplyIntent": null
  },
  "aiInsights": {
    "bestSendingDay": "Wednesday",
    "optimalTime": "10:00",
    "responsePattern": null,
    "interestProducts": [
      "smart-toys"
    ],
    "stylePreference": "formal",
    "lastDistillMatchScore": 0,
    "engagementScore": 32,
    "priorityScore": 50
  },
  "tags": [],
  "metadata": {
    "createdAt": "2024-07-14T14:32:53.896Z",
    "updatedAt": "2026-05-09T14:32:53.896Z",
    "version": 1,
    "dataHash": "592eeb103dd870ea",
    "importSource": "system-initialization",
    "importBatch": "batch-001-2026-05-09"
  }
}