{
  "clientId": "CLT-07256",
  "emailAccount": "account-073",
  "basicInfo": {
    "name": "Susan Sanchez",
    "email": "susan.sanchez@company.com",
    "company": "Zenith Williams ToyBox",
    "website": "www.zenithwilliamstoybox.com",
    "country": "US",
    "countryName": "United States",
    "timezone": "America/New_York",
    "language": "en",
    "phone": "+1927742064130",
    "position": "Owner",
    "linkedIn": ""
  },
  "businessProfile": {
    "clientLevel": "C",
    "industry": "E-commerce Platform",
    "purchaseCategory": [
      "educational"
    ],
    "estimatedVolume": "small",
    "companySize": "501-1000",
    "annualRevenue": "$100K-$500K",
    "firstContactExhibition": "Nuremberg Toy Fair",
    "firstContactYear": 2015,
    "lastContactDate": "2025-12-18",
    "status": "churned",
    "preferredContactTime": "12:00",
    "notes": ""
  },
  "communicationHistory": {
    "totalEmailsSent": 5,
    "totalRepliesReceived": 1,
    "lastReplyDate": null,
    "replyRate": 20,
    "lastReplyIntent": null
  },
  "aiInsights": {
    "bestSendingDay": "Tuesday",
    "optimalTime": "15:00",
    "responsePattern": null,
    "interestProducts": [
      "educational"
    ],
    "stylePreference": "friendly",
    "lastDistillMatchScore": 0,
    "engagementScore": 13,
    "priorityScore": 59
  },
  "tags": [],
  "metadata": {
    "createdAt": "2024-11-22T14:32:53.895Z",
    "updatedAt": "2026-05-09T14:32:53.895Z",
    "version": 1,
    "dataHash": "6034259008a5920b",
    "importSource": "system-initialization",
    "importBatch": "batch-001-2026-05-09"
  }
}