{
  "clientId": "CLT-02268",
  "emailAccount": "account-023",
  "basicInfo": {
    "name": "Pamela Garcia",
    "email": "pamela.garcia@company.com.au",
    "company": "Super Hernandez WonderToys",
    "website": "www.superhernandezwondertoys.com.au",
    "country": "AU",
    "countryName": "Australia",
    "timezone": "Australia/Sydney",
    "language": "en",
    "phone": "+1781087502230",
    "position": "Owner",
    "linkedIn": ""
  },
  "businessProfile": {
    "clientLevel": "B",
    "industry": "Distributor",
    "purchaseCategory": [
      "infant-toddler"
    ],
    "estimatedVolume": "medium",
    "companySize": "51-200",
    "annualRevenue": "$<100K",
    "firstContactExhibition": "Moscow Toy Show",
    "firstContactYear": 2026,
    "lastContactDate": "2025-01-23",
    "status": "sleeping",
    "preferredContactTime": "10:00",
    "notes": ""
  },
  "communicationHistory": {
    "totalEmailsSent": 8,
    "totalRepliesReceived": 0,
    "lastReplyDate": null,
    "replyRate": 0,
    "lastReplyIntent": null
  },
  "aiInsights": {
    "bestSendingDay": "Wednesday",
    "optimalTime": "14:00",
    "responsePattern": null,
    "interestProducts": [
      "infant-toddler"
    ],
    "stylePreference": "formal",
    "lastDistillMatchScore": 0,
    "engagementScore": 39,
    "priorityScore": 80
  },
  "tags": [],
  "metadata": {
    "createdAt": "2023-06-04T14:32:52.411Z",
    "updatedAt": "2026-05-09T14:32:52.411Z",
    "version": 1,
    "dataHash": "c5a9a0148236265a",
    "importSource": "system-initialization",
    "importBatch": "batch-001-2026-05-09"
  }
}