{
  "clientId": "CLT-02208",
  "emailAccount": "account-023",
  "basicInfo": {
    "name": "Charles Thomas",
    "email": "charles.thomas@yahoo.com",
    "company": "Moon Young Little Stars",
    "website": "www.moonyounglittlestars.com",
    "country": "VN",
    "countryName": "Vietnam",
    "timezone": "Asia/Ho_Chi_Minh",
    "language": "en",
    "phone": "+4025516484871",
    "position": "Category Manager",
    "linkedIn": ""
  },
  "businessProfile": {
    "clientLevel": "C",
    "industry": "Toy Retail Chain",
    "purchaseCategory": [
      "smart-toys",
      "classic-toys"
    ],
    "estimatedVolume": "small",
    "companySize": "51-200",
    "annualRevenue": "$<100K",
    "firstContactExhibition": "Hong Kong Toys & Games Fair",
    "firstContactYear": 2016,
    "lastContactDate": "2026-03-10",
    "status": "active",
    "preferredContactTime": "10:00",
    "notes": ""
  },
  "communicationHistory": {
    "totalEmailsSent": 14,
    "totalRepliesReceived": 7,
    "lastReplyDate": "2026-04-11",
    "replyRate": 50,
    "lastReplyIntent": null
  },
  "aiInsights": {
    "bestSendingDay": "Tuesday",
    "optimalTime": "09:00",
    "responsePattern": "price-sensitive",
    "interestProducts": [
      "smart-toys",
      "classic-toys"
    ],
    "stylePreference": "professional",
    "lastDistillMatchScore": 0,
    "engagementScore": 69,
    "priorityScore": 64
  },
  "tags": [],
  "metadata": {
    "createdAt": "2023-09-26T14:32:52.392Z",
    "updatedAt": "2026-05-09T14:32:52.392Z",
    "version": 1,
    "dataHash": "968acc2f4109b54f",
    "importSource": "system-initialization",
    "importBatch": "batch-001-2026-05-09"
  }
}