{
  "clientId": "CLT-02231",
  "emailAccount": "account-023",
  "basicInfo": {
    "name": "Betty Adams",
    "email": "betty.adams@yahoo.com",
    "company": "Zenith Harris Enterprises",
    "website": "www.zenithharrisenterprises.com",
    "country": "CL",
    "countryName": "Chile",
    "timezone": "America/Santiago",
    "language": "en",
    "phone": "+641120535777",
    "position": "Owner",
    "linkedIn": ""
  },
  "businessProfile": {
    "clientLevel": "B",
    "industry": "Gift Shop Chain",
    "purchaseCategory": [
      "rc-toys",
      "educational"
    ],
    "estimatedVolume": "medium",
    "companySize": "51-200",
    "annualRevenue": "$<100K",
    "firstContactExhibition": "São Paulo Toy Fair",
    "firstContactYear": 2022,
    "lastContactDate": "2026-04-24",
    "status": "active",
    "preferredContactTime": "12:00",
    "notes": ""
  },
  "communicationHistory": {
    "totalEmailsSent": 12,
    "totalRepliesReceived": 6,
    "lastReplyDate": null,
    "replyRate": 50,
    "lastReplyIntent": null
  },
  "aiInsights": {
    "bestSendingDay": "Wednesday",
    "optimalTime": "13:00",
    "responsePattern": "price-sensitive",
    "interestProducts": [
      "rc-toys",
      "educational"
    ],
    "stylePreference": "friendly",
    "lastDistillMatchScore": 0,
    "engagementScore": 79,
    "priorityScore": 85
  },
  "tags": [],
  "metadata": {
    "createdAt": "2024-08-10T14:32:52.400Z",
    "updatedAt": "2026-05-09T14:32:52.400Z",
    "version": 1,
    "dataHash": "04be8fcebfdc5fd4",
    "importSource": "system-initialization",
    "importBatch": "batch-001-2026-05-09"
  }
}