{
  "clientId": "CLT-03166",
  "emailAccount": "account-032",
  "basicInfo": {
    "name": "George Martin",
    "email": "george.martin@yahoo.com",
    "company": "Bright Rodriguez Little Stars",
    "website": "www.brightrodriguezlittlestars.com",
    "country": "US",
    "countryName": "United States",
    "timezone": "America/New_York",
    "language": "en",
    "phone": "+1698071667798",
    "position": "Purchasing Manager",
    "linkedIn": ""
  },
  "businessProfile": {
    "clientLevel": "C",
    "industry": "Department Store",
    "purchaseCategory": [
      "classic-toys",
      "rc-toys"
    ],
    "estimatedVolume": "small",
    "companySize": "201-500",
    "annualRevenue": "$100K-$500K",
    "firstContactExhibition": "Mexico Toy Expo",
    "firstContactYear": 2023,
    "lastContactDate": "2024-09-13",
    "status": "sleeping",
    "preferredContactTime": "09:00",
    "notes": ""
  },
  "communicationHistory": {
    "totalEmailsSent": 6,
    "totalRepliesReceived": 1,
    "lastReplyDate": null,
    "replyRate": 17,
    "lastReplyIntent": null
  },
  "aiInsights": {
    "bestSendingDay": "Monday",
    "optimalTime": "10:00",
    "responsePattern": null,
    "interestProducts": [
      "classic-toys",
      "rc-toys"
    ],
    "stylePreference": "formal",
    "lastDistillMatchScore": 0,
    "engagementScore": 24,
    "priorityScore": 66
  },
  "tags": [],
  "metadata": {
    "createdAt": "2026-01-28T14:32:52.692Z",
    "updatedAt": "2026-05-09T14:32:52.692Z",
    "version": 1,
    "dataHash": "e01506a637f3cd7b",
    "importSource": "system-initialization",
    "importBatch": "batch-001-2026-05-09"
  }
}