{
  "clientId": "CLT-02955",
  "emailAccount": "account-030",
  "basicInfo": {
    "name": "Mary Nguyen",
    "email": "mary.nguyen@gmail.com",
    "company": "Omega Adams Toys & Games",
    "website": "www.omegaadamstoysgames.com.au",
    "country": "AU",
    "countryName": "Australia",
    "timezone": "Australia/Sydney",
    "language": "en",
    "phone": "+6328200346826",
    "position": "Director",
    "linkedIn": ""
  },
  "businessProfile": {
    "clientLevel": "A",
    "industry": "Wholesaler",
    "purchaseCategory": [
      "rc-toys",
      "educational",
      "outdoor"
    ],
    "estimatedVolume": "large",
    "companySize": "201-500",
    "annualRevenue": "$2M-$10M",
    "firstContactExhibition": "New York Toy Fair",
    "firstContactYear": 2026,
    "lastContactDate": "2025-08-19",
    "status": "churned",
    "preferredContactTime": "14:00",
    "notes": ""
  },
  "communicationHistory": {
    "totalEmailsSent": 3,
    "totalRepliesReceived": 0,
    "lastReplyDate": null,
    "replyRate": 0,
    "lastReplyIntent": null
  },
  "aiInsights": {
    "bestSendingDay": "Tuesday",
    "optimalTime": "15:00",
    "responsePattern": null,
    "interestProducts": [
      "rc-toys",
      "educational"
    ],
    "stylePreference": "direct",
    "lastDistillMatchScore": 0,
    "engagementScore": 21,
    "priorityScore": 97
  },
  "tags": [],
  "metadata": {
    "createdAt": "2021-10-24T14:32:52.628Z",
    "updatedAt": "2026-05-09T14:32:52.628Z",
    "version": 1,
    "dataHash": "7eff08f8eb726dac",
    "importSource": "system-initialization",
    "importBatch": "batch-001-2026-05-09"
  }
}