{
  "clientId": "CLT-04857",
  "emailAccount": "account-049",
  "basicInfo": {
    "name": "Christopher Wilson",
    "email": "christopher.wilson@yahoo.co.uk",
    "company": "Ultra Green Imports",
    "website": "www.ultragreenimports.co.uk",
    "country": "GB",
    "countryName": "United Kingdom",
    "timezone": "Europe/London",
    "language": "en",
    "phone": "+4916921120498",
    "position": "Procurement Officer",
    "linkedIn": ""
  },
  "businessProfile": {
    "clientLevel": "C",
    "industry": "Distributor",
    "purchaseCategory": [
      "infant-toddler"
    ],
    "estimatedVolume": "small",
    "companySize": "51-200",
    "annualRevenue": "$<100K",
    "firstContactExhibition": "London Toy Fair",
    "firstContactYear": 2021,
    "lastContactDate": "2024-11-01",
    "status": "churned",
    "preferredContactTime": "14:00",
    "notes": ""
  },
  "communicationHistory": {
    "totalEmailsSent": 5,
    "totalRepliesReceived": 2,
    "lastReplyDate": null,
    "replyRate": 40,
    "lastReplyIntent": null
  },
  "aiInsights": {
    "bestSendingDay": "Wednesday",
    "optimalTime": "14:00",
    "responsePattern": null,
    "interestProducts": [
      "infant-toddler"
    ],
    "stylePreference": "professional",
    "lastDistillMatchScore": 0,
    "engagementScore": 11,
    "priorityScore": 66
  },
  "tags": [],
  "metadata": {
    "createdAt": "2021-07-02T14:32:53.205Z",
    "updatedAt": "2026-05-09T14:32:53.205Z",
    "version": 1,
    "dataHash": "f5172b394d3a0954",
    "importSource": "system-initialization",
    "importBatch": "batch-001-2026-05-09"
  }
}