{
  "clientId": "CLT-07861",
  "emailAccount": "account-079",
  "basicInfo": {
    "name": "Donna Ramirez",
    "email": "donna.ramirez@yahoo.com",
    "company": "Playful Martinez PlayTime",
    "website": "www.playfulmartinezplaytime.com",
    "country": "IL",
    "countryName": "Israel",
    "timezone": "Asia/Jerusalem",
    "language": "en",
    "phone": "+2171063949230",
    "position": "Owner",
    "linkedIn": ""
  },
  "businessProfile": {
    "clientLevel": "C",
    "industry": "Online Marketplace",
    "purchaseCategory": [
      "outdoor",
      "educational"
    ],
    "estimatedVolume": "small",
    "companySize": "11-50",
    "annualRevenue": "$100K-$500K",
    "firstContactExhibition": "Nuremberg Toy Fair",
    "firstContactYear": 2015,
    "lastContactDate": "2025-01-09",
    "status": "sleeping",
    "preferredContactTime": "10:00",
    "notes": ""
  },
  "communicationHistory": {
    "totalEmailsSent": 8,
    "totalRepliesReceived": 2,
    "lastReplyDate": null,
    "replyRate": 25,
    "lastReplyIntent": null
  },
  "aiInsights": {
    "bestSendingDay": "Thursday",
    "optimalTime": "10:00",
    "responsePattern": null,
    "interestProducts": [
      "outdoor",
      "educational"
    ],
    "stylePreference": "formal",
    "lastDistillMatchScore": 0,
    "engagementScore": 5,
    "priorityScore": 64
  },
  "tags": [],
  "metadata": {
    "createdAt": "2021-11-21T14:32:54.071Z",
    "updatedAt": "2026-05-09T14:32:54.071Z",
    "version": 1,
    "dataHash": "9ce5826d7f4f58b3",
    "importSource": "system-initialization",
    "importBatch": "batch-001-2026-05-09"
  }
}