{
  "clientId": "CLT-07007",
  "emailAccount": "account-071",
  "basicInfo": {
    "name": "Pamela Harris",
    "email": "pamela.harris@company.fr",
    "company": "Imaginative Johnson Inc.",
    "website": "www.imaginativejohnsoninc.fr",
    "country": "FR",
    "countryName": "France",
    "timezone": "Europe/Paris",
    "language": "fr",
    "phone": "+2219931254571",
    "position": "Buyer",
    "linkedIn": ""
  },
  "businessProfile": {
    "clientLevel": "C",
    "industry": "Import Export Company",
    "purchaseCategory": [
      "rc-toys",
      "classic-toys"
    ],
    "estimatedVolume": "small",
    "companySize": "501-1000",
    "annualRevenue": "$<100K",
    "firstContactExhibition": "Mexico Toy Expo",
    "firstContactYear": 2015,
    "lastContactDate": "2024-11-25",
    "status": "sleeping",
    "preferredContactTime": "10:00",
    "notes": ""
  },
  "communicationHistory": {
    "totalEmailsSent": 2,
    "totalRepliesReceived": 2,
    "lastReplyDate": null,
    "replyRate": 100,
    "lastReplyIntent": null
  },
  "aiInsights": {
    "bestSendingDay": "Wednesday",
    "optimalTime": "10:00",
    "responsePattern": null,
    "interestProducts": [
      "rc-toys",
      "classic-toys"
    ],
    "stylePreference": "friendly",
    "lastDistillMatchScore": 0,
    "engagementScore": 10,
    "priorityScore": 66
  },
  "tags": [],
  "metadata": {
    "createdAt": "2021-09-23T14:32:53.822Z",
    "updatedAt": "2026-05-09T14:32:53.822Z",
    "version": 1,
    "dataHash": "6d5fb5f0c3330163",
    "importSource": "system-initialization",
    "importBatch": "batch-001-2026-05-09"
  }
}