{
  "clientId": "CLT-05765",
  "emailAccount": "account-058",
  "basicInfo": {
    "name": "Barbara Nguyen",
    "email": "barbara.nguyen@company.com",
    "company": "Fantastic Lewis WonderToys",
    "website": "www.fantasticlewiswondertoys.com",
    "country": "MX",
    "countryName": "Mexico",
    "timezone": "America/Mexico_City",
    "language": "en",
    "phone": "+1383251103832",
    "position": "Director",
    "linkedIn": ""
  },
  "businessProfile": {
    "clientLevel": "B",
    "industry": "E-commerce Platform",
    "purchaseCategory": [
      "educational",
      "outdoor",
      "classic-toys"
    ],
    "estimatedVolume": "medium",
    "companySize": "1-10",
    "annualRevenue": "$<100K",
    "firstContactExhibition": "Hong Kong Toys & Games Fair",
    "firstContactYear": 2022,
    "lastContactDate": "2026-04-29",
    "status": "active",
    "preferredContactTime": "09:00",
    "notes": ""
  },
  "communicationHistory": {
    "totalEmailsSent": 18,
    "totalRepliesReceived": 2,
    "lastReplyDate": "2026-04-12",
    "replyRate": 11,
    "lastReplyIntent": null
  },
  "aiInsights": {
    "bestSendingDay": "Wednesday",
    "optimalTime": "09:00",
    "responsePattern": "quick-responder",
    "interestProducts": [
      "educational",
      "outdoor"
    ],
    "stylePreference": "professional",
    "lastDistillMatchScore": 0,
    "engagementScore": 94,
    "priorityScore": 77
  },
  "tags": [],
  "metadata": {
    "createdAt": "2024-03-08T14:32:53.461Z",
    "updatedAt": "2026-05-09T14:32:53.461Z",
    "version": 1,
    "dataHash": "151fae0a0aad5e01",
    "importSource": "system-initialization",
    "importBatch": "batch-001-2026-05-09"
  }
}