{
  "clientId": "CLT-06505",
  "emailAccount": "account-066",
  "basicInfo": {
    "name": "Janet Ramirez",
    "email": "janet.ramirez@gmail.com",
    "company": "Fantastic Hill Distribution",
    "website": "www.fantastichilldistribution.com",
    "country": "TH",
    "countryName": "Thailand",
    "timezone": "Asia/Bangkok",
    "language": "en",
    "phone": "+3654373079741",
    "position": "Category Manager",
    "linkedIn": ""
  },
  "businessProfile": {
    "clientLevel": "B",
    "industry": "Department Store",
    "purchaseCategory": [
      "infant-toddler"
    ],
    "estimatedVolume": "medium",
    "companySize": "11-50",
    "annualRevenue": "$500K-$2M",
    "firstContactExhibition": "Dubai Toy Expo",
    "firstContactYear": 2025,
    "lastContactDate": "2026-04-21",
    "status": "active",
    "preferredContactTime": "12:00",
    "notes": ""
  },
  "communicationHistory": {
    "totalEmailsSent": 4,
    "totalRepliesReceived": 8,
    "lastReplyDate": null,
    "replyRate": 200,
    "lastReplyIntent": null
  },
  "aiInsights": {
    "bestSendingDay": "Tuesday",
    "optimalTime": "13:00",
    "responsePattern": "price-sensitive",
    "interestProducts": [
      "infant-toddler"
    ],
    "stylePreference": "direct",
    "lastDistillMatchScore": 0,
    "engagementScore": 68,
    "priorityScore": 84
  },
  "tags": [],
  "metadata": {
    "createdAt": "2024-04-18T14:32:53.675Z",
    "updatedAt": "2026-05-09T14:32:53.675Z",
    "version": 1,
    "dataHash": "21af084e1a03e75c",
    "importSource": "system-initialization",
    "importBatch": "batch-001-2026-05-09"
  }
}