{
  "clientId": "CLT-06565",
  "emailAccount": "account-066",
  "basicInfo": {
    "name": "Eric Gonzalez",
    "email": "eric.gonzalez@gmail.com",
    "company": "Super Ramirez International",
    "website": "www.superramirezinternational.de",
    "country": "DE",
    "countryName": "Germany",
    "timezone": "Europe/Berlin",
    "language": "de",
    "phone": "+5824733485952",
    "position": "CEO",
    "linkedIn": ""
  },
  "businessProfile": {
    "clientLevel": "B",
    "industry": "Wholesaler",
    "purchaseCategory": [
      "rc-toys",
      "outdoor",
      "educational"
    ],
    "estimatedVolume": "medium",
    "companySize": "201-500",
    "annualRevenue": "$100K-$500K",
    "firstContactExhibition": "Hong Kong Toys & Games Fair",
    "firstContactYear": 2024,
    "lastContactDate": "2026-02-19",
    "status": "active",
    "preferredContactTime": "14:00",
    "notes": ""
  },
  "communicationHistory": {
    "totalEmailsSent": 3,
    "totalRepliesReceived": 4,
    "lastReplyDate": "2026-04-29",
    "replyRate": 133,
    "lastReplyIntent": null
  },
  "aiInsights": {
    "bestSendingDay": "Wednesday",
    "optimalTime": "09:00",
    "responsePattern": "price-sensitive",
    "interestProducts": [
      "rc-toys",
      "outdoor"
    ],
    "stylePreference": "professional",
    "lastDistillMatchScore": 0,
    "engagementScore": 65,
    "priorityScore": 89
  },
  "tags": [],
  "metadata": {
    "createdAt": "2024-07-18T14:32:53.692Z",
    "updatedAt": "2026-05-09T14:32:53.692Z",
    "version": 1,
    "dataHash": "d8b4d303f75ad730",
    "importSource": "system-initialization",
    "importBatch": "batch-001-2026-05-09"
  }
}