{
  "clientId": "CLT-04554",
  "emailAccount": "account-046",
  "basicInfo": {
    "name": "Patricia Ramirez",
    "email": "patricia.ramirez@company.nl",
    "company": "Omega Hall PlayTime",
    "website": "www.omegahallplaytime.com",
    "country": "NL",
    "countryName": "Netherlands",
    "timezone": "Europe/Amsterdam",
    "language": "en",
    "phone": "+5138113452156",
    "position": "CEO",
    "linkedIn": ""
  },
  "businessProfile": {
    "clientLevel": "B",
    "industry": "Online Marketplace",
    "purchaseCategory": [
      "classic-toys",
      "infant-toddler",
      "rc-toys"
    ],
    "estimatedVolume": "medium",
    "companySize": "201-500",
    "annualRevenue": "$<100K",
    "firstContactExhibition": "Mexico Toy Expo",
    "firstContactYear": 2019,
    "lastContactDate": "2025-05-04",
    "status": "churned",
    "preferredContactTime": "14:00",
    "notes": ""
  },
  "communicationHistory": {
    "totalEmailsSent": 9,
    "totalRepliesReceived": 0,
    "lastReplyDate": null,
    "replyRate": 0,
    "lastReplyIntent": null
  },
  "aiInsights": {
    "bestSendingDay": "Monday",
    "optimalTime": "11:00",
    "responsePattern": null,
    "interestProducts": [
      "classic-toys",
      "infant-toddler"
    ],
    "stylePreference": "formal",
    "lastDistillMatchScore": 0,
    "engagementScore": 6,
    "priorityScore": 86
  },
  "tags": [],
  "metadata": {
    "createdAt": "2025-03-04T14:32:53.113Z",
    "updatedAt": "2026-05-09T14:32:53.113Z",
    "version": 1,
    "dataHash": "40cc068f360f0c4f",
    "importSource": "system-initialization",
    "importBatch": "batch-001-2026-05-09"
  }
}