{
  "clientId": "CLT-04532",
  "emailAccount": "account-046",
  "basicInfo": {
    "name": "Patricia Clark",
    "email": "patricia.clark@gmail.com",
    "company": "Prime Jones DreamPlay",
    "website": "www.primejonesdreamplay.com",
    "country": "CN",
    "countryName": "China",
    "timezone": "Asia/Shanghai",
    "language": "en",
    "phone": "+7161862667279",
    "position": "Buyer",
    "linkedIn": ""
  },
  "businessProfile": {
    "clientLevel": "A",
    "industry": "Specialty Store",
    "purchaseCategory": [
      "rc-toys",
      "classic-toys",
      "outdoor"
    ],
    "estimatedVolume": "large",
    "companySize": "1-10",
    "annualRevenue": "$50M+",
    "firstContactExhibition": "New York Toy Fair",
    "firstContactYear": 2021,
    "lastContactDate": "2026-03-11",
    "status": "active",
    "preferredContactTime": "09:00",
    "notes": ""
  },
  "communicationHistory": {
    "totalEmailsSent": 12,
    "totalRepliesReceived": 2,
    "lastReplyDate": "2026-05-07",
    "replyRate": 17,
    "lastReplyIntent": null
  },
  "aiInsights": {
    "bestSendingDay": "Thursday",
    "optimalTime": "09:00",
    "responsePattern": "quick-responder",
    "interestProducts": [
      "rc-toys",
      "classic-toys"
    ],
    "stylePreference": "friendly",
    "lastDistillMatchScore": 0,
    "engagementScore": 61,
    "priorityScore": 96
  },
  "tags": [],
  "metadata": {
    "createdAt": "2025-10-31T14:32:53.106Z",
    "updatedAt": "2026-05-09T14:32:53.106Z",
    "version": 1,
    "dataHash": "1d2c79fa2f33705b",
    "importSource": "system-initialization",
    "importBatch": "batch-001-2026-05-09"
  }
}