{
  "clientId": "CLT-00312",
  "emailAccount": "account-004",
  "basicInfo": {
    "name": "Kenneth Lopez",
    "email": "kenneth.lopez@libero.it",
    "company": "Whimsical Clark Imports",
    "website": "www.whimsicalclarkimports.com",
    "country": "IT",
    "countryName": "Italy",
    "timezone": "Europe/Rome",
    "language": "en",
    "phone": "+2124008779699",
    "position": "CEO",
    "linkedIn": ""
  },
  "businessProfile": {
    "clientLevel": "B",
    "industry": "Online Marketplace",
    "purchaseCategory": [
      "infant-toddler",
      "outdoor"
    ],
    "estimatedVolume": "medium",
    "companySize": "1-10",
    "annualRevenue": "$50M+",
    "firstContactExhibition": "London Toy Fair",
    "firstContactYear": 2015,
    "lastContactDate": "2026-05-07",
    "status": "sleeping",
    "preferredContactTime": "15:00",
    "notes": ""
  },
  "communicationHistory": {
    "totalEmailsSent": 2,
    "totalRepliesReceived": 2,
    "lastReplyDate": null,
    "replyRate": 100,
    "lastReplyIntent": null
  },
  "aiInsights": {
    "bestSendingDay": "Thursday",
    "optimalTime": "15:00",
    "responsePattern": null,
    "interestProducts": [
      "infant-toddler",
      "outdoor"
    ],
    "stylePreference": "direct",
    "lastDistillMatchScore": 0,
    "engagementScore": 12,
    "priorityScore": 85
  },
  "tags": [],
  "metadata": {
    "createdAt": "2022-02-21T14:32:51.790Z",
    "updatedAt": "2026-05-09T14:32:51.790Z",
    "version": 1,
    "dataHash": "b796fa947a47ea96",
    "importSource": "system-initialization",
    "importBatch": "batch-001-2026-05-09"
  }
}