{
  "clientId": "CLT-00342",
  "emailAccount": "account-004",
  "basicInfo": {
    "name": "Susan Perez",
    "email": "susan.perez@outlook.com",
    "company": "Ultra White Trading",
    "website": "www.ultrawhitetrading.ca",
    "country": "CA",
    "countryName": "Canada",
    "timezone": "America/Toronto",
    "language": "en",
    "phone": "+7815241397797",
    "position": "Purchasing Manager",
    "linkedIn": ""
  },
  "businessProfile": {
    "clientLevel": "B",
    "industry": "E-commerce Platform",
    "purchaseCategory": [
      "outdoor",
      "educational"
    ],
    "estimatedVolume": "medium",
    "companySize": "51-200",
    "annualRevenue": "$<100K",
    "firstContactExhibition": "Bangkok Toys & Games Fair",
    "firstContactYear": 2024,
    "lastContactDate": "2026-02-19",
    "status": "active",
    "preferredContactTime": "13:00",
    "notes": ""
  },
  "communicationHistory": {
    "totalEmailsSent": 2,
    "totalRepliesReceived": 8,
    "lastReplyDate": null,
    "replyRate": 400,
    "lastReplyIntent": null
  },
  "aiInsights": {
    "bestSendingDay": "Thursday",
    "optimalTime": "13:00",
    "responsePattern": "considerate",
    "interestProducts": [
      "outdoor",
      "educational"
    ],
    "stylePreference": "formal",
    "lastDistillMatchScore": 0,
    "engagementScore": 76,
    "priorityScore": 86
  },
  "tags": [],
  "metadata": {
    "createdAt": "2024-08-06T14:32:51.799Z",
    "updatedAt": "2026-05-09T14:32:51.799Z",
    "version": 1,
    "dataHash": "c0522ff81eb0a6af",
    "importSource": "system-initialization",
    "importBatch": "batch-001-2026-05-09"
  }
}