{
  "clientId": "CLT-02584",
  "emailAccount": "account-026",
  "basicInfo": {
    "name": "Gregory Carter",
    "email": "gregory.carter@company.ca",
    "company": "Bright Green DreamPlay",
    "website": "www.brightgreendreamplay.ca",
    "country": "CA",
    "countryName": "Canada",
    "timezone": "America/Toronto",
    "language": "en",
    "phone": "+7411060936900",
    "position": "Category Manager",
    "linkedIn": ""
  },
  "businessProfile": {
    "clientLevel": "C",
    "industry": "Distributor",
    "purchaseCategory": [
      "infant-toddler"
    ],
    "estimatedVolume": "small",
    "companySize": "11-50",
    "annualRevenue": "$100K-$500K",
    "firstContactExhibition": "Nuremberg Toy Fair",
    "firstContactYear": 2023,
    "lastContactDate": "2026-04-03",
    "status": "active",
    "preferredContactTime": "11:00",
    "notes": ""
  },
  "communicationHistory": {
    "totalEmailsSent": 4,
    "totalRepliesReceived": 7,
    "lastReplyDate": "2026-04-12",
    "replyRate": 175,
    "lastReplyIntent": null
  },
  "aiInsights": {
    "bestSendingDay": "Monday",
    "optimalTime": "16:00",
    "responsePattern": "quality-focused",
    "interestProducts": [
      "infant-toddler"
    ],
    "stylePreference": "direct",
    "lastDistillMatchScore": 0,
    "engagementScore": 76,
    "priorityScore": 56
  },
  "tags": [],
  "metadata": {
    "createdAt": "2023-03-26T14:32:52.514Z",
    "updatedAt": "2026-05-09T14:32:52.514Z",
    "version": 1,
    "dataHash": "554c3c7226c0128b",
    "importSource": "system-initialization",
    "importBatch": "batch-001-2026-05-09"
  }
}