{
  "clientId": "CLT-05959",
  "emailAccount": "account-060",
  "basicInfo": {
    "name": "Kathleen Smith",
    "email": "kathleen.smith@company.fr",
    "company": "Happy Garcia Kids World",
    "website": "www.happygarciakidsworld.fr",
    "country": "FR",
    "countryName": "France",
    "timezone": "Europe/Paris",
    "language": "fr",
    "phone": "+2096023472889",
    "position": "Category Manager",
    "linkedIn": ""
  },
  "businessProfile": {
    "clientLevel": "B",
    "industry": "Import Export Company",
    "purchaseCategory": [
      "educational",
      "outdoor",
      "smart-toys"
    ],
    "estimatedVolume": "medium",
    "companySize": "501-1000",
    "annualRevenue": "$2M-$10M",
    "firstContactExhibition": "Tokyo Gift Show",
    "firstContactYear": 2023,
    "lastContactDate": "2024-07-13",
    "status": "churned",
    "preferredContactTime": "11:00",
    "notes": ""
  },
  "communicationHistory": {
    "totalEmailsSent": 14,
    "totalRepliesReceived": 1,
    "lastReplyDate": null,
    "replyRate": 7,
    "lastReplyIntent": null
  },
  "aiInsights": {
    "bestSendingDay": "Friday",
    "optimalTime": "15:00",
    "responsePattern": null,
    "interestProducts": [
      "educational",
      "outdoor"
    ],
    "stylePreference": "formal",
    "lastDistillMatchScore": 0,
    "engagementScore": 19,
    "priorityScore": 76
  },
  "tags": [],
  "metadata": {
    "createdAt": "2021-08-02T14:32:53.517Z",
    "updatedAt": "2026-05-09T14:32:53.517Z",
    "version": 1,
    "dataHash": "290db3045f72ad4a",
    "importSource": "system-initialization",
    "importBatch": "batch-001-2026-05-09"
  }
}