{
  "clientId": "CLT-04384",
  "emailAccount": "account-044",
  "basicInfo": {
    "name": "Brian Martin",
    "email": "brian.martin@gmail.com",
    "company": "Happy Lewis Toys & Games",
    "website": "www.happylewistoysgames.ca",
    "country": "CA",
    "countryName": "Canada",
    "timezone": "America/Toronto",
    "language": "en",
    "phone": "+1756451580002",
    "position": "Owner",
    "linkedIn": ""
  },
  "businessProfile": {
    "clientLevel": "C",
    "industry": "Online Marketplace",
    "purchaseCategory": [
      "outdoor",
      "rc-toys"
    ],
    "estimatedVolume": "small",
    "companySize": "51-200",
    "annualRevenue": "$10M-$50M",
    "firstContactExhibition": "Bangkok Toys & Games Fair",
    "firstContactYear": 2015,
    "lastContactDate": "2024-05-28",
    "status": "sleeping",
    "preferredContactTime": "14:00",
    "notes": ""
  },
  "communicationHistory": {
    "totalEmailsSent": 11,
    "totalRepliesReceived": 1,
    "lastReplyDate": null,
    "replyRate": 9,
    "lastReplyIntent": null
  },
  "aiInsights": {
    "bestSendingDay": "Tuesday",
    "optimalTime": "11:00",
    "responsePattern": null,
    "interestProducts": [
      "outdoor",
      "rc-toys"
    ],
    "stylePreference": "professional",
    "lastDistillMatchScore": 0,
    "engagementScore": 14,
    "priorityScore": 59
  },
  "tags": [],
  "metadata": {
    "createdAt": "2024-02-08T14:32:53.059Z",
    "updatedAt": "2026-05-09T14:32:53.059Z",
    "version": 1,
    "dataHash": "a9dd3a16ce3262c6",
    "importSource": "system-initialization",
    "importBatch": "batch-001-2026-05-09"
  }
}