{
  "clientId": "CLT-07530",
  "emailAccount": "account-076",
  "basicInfo": {
    "name": "Andrew Johnson",
    "email": "andrew.johnson@gmail.com",
    "company": "Sun Campbell International",
    "website": "www.suncampbellinternational.com",
    "country": "ID",
    "countryName": "Indonesia",
    "timezone": "Asia/Jakarta",
    "language": "en",
    "phone": "+862749963128",
    "position": "Owner",
    "linkedIn": ""
  },
  "businessProfile": {
    "clientLevel": "B",
    "industry": "Wholesaler",
    "purchaseCategory": [
      "outdoor",
      "classic-toys"
    ],
    "estimatedVolume": "medium",
    "companySize": "11-50",
    "annualRevenue": "$500K-$2M",
    "firstContactExhibition": "Dubai Toy Expo",
    "firstContactYear": 2015,
    "lastContactDate": "2024-06-08",
    "status": "sleeping",
    "preferredContactTime": "09:00",
    "notes": ""
  },
  "communicationHistory": {
    "totalEmailsSent": 2,
    "totalRepliesReceived": 1,
    "lastReplyDate": null,
    "replyRate": 50,
    "lastReplyIntent": null
  },
  "aiInsights": {
    "bestSendingDay": "Friday",
    "optimalTime": "15:00",
    "responsePattern": null,
    "interestProducts": [
      "outdoor",
      "classic-toys"
    ],
    "stylePreference": "formal",
    "lastDistillMatchScore": 0,
    "engagementScore": 19,
    "priorityScore": 86
  },
  "tags": [],
  "metadata": {
    "createdAt": "2023-10-11T14:32:53.976Z",
    "updatedAt": "2026-05-09T14:32:53.976Z",
    "version": 1,
    "dataHash": "12c637f1abce1f52",
    "importSource": "system-initialization",
    "importBatch": "batch-001-2026-05-09"
  }
}