{
  "clientId": "CLT-06033",
  "emailAccount": "account-061",
  "basicInfo": {
    "name": "Stephanie Carter",
    "email": "stephanie.carter@company.es",
    "company": "Happy Allen Distribution",
    "website": "www.happyallendistribution.es",
    "country": "ES",
    "countryName": "Spain",
    "timezone": "Europe/Madrid",
    "language": "es",
    "phone": "+6316545772256",
    "position": "Owner",
    "linkedIn": ""
  },
  "businessProfile": {
    "clientLevel": "C",
    "industry": "Wholesaler",
    "purchaseCategory": [
      "infant-toddler"
    ],
    "estimatedVolume": "small",
    "companySize": "1000+",
    "annualRevenue": "$500K-$2M",
    "firstContactExhibition": "Shanghai Toy Expo",
    "firstContactYear": 2025,
    "lastContactDate": "2025-04-18",
    "status": "churned",
    "preferredContactTime": "14:00",
    "notes": ""
  },
  "communicationHistory": {
    "totalEmailsSent": 2,
    "totalRepliesReceived": 2,
    "lastReplyDate": null,
    "replyRate": 100,
    "lastReplyIntent": null
  },
  "aiInsights": {
    "bestSendingDay": "Tuesday",
    "optimalTime": "12:00",
    "responsePattern": null,
    "interestProducts": [
      "infant-toddler"
    ],
    "stylePreference": "direct",
    "lastDistillMatchScore": 0,
    "engagementScore": 8,
    "priorityScore": 52
  },
  "tags": [],
  "metadata": {
    "createdAt": "2024-09-21T14:32:53.539Z",
    "updatedAt": "2026-05-09T14:32:53.539Z",
    "version": 1,
    "dataHash": "7a1a933a74617a99",
    "importSource": "system-initialization",
    "importBatch": "batch-001-2026-05-09"
  }
}