{
  "clientId": "CLT-06046",
  "emailAccount": "account-061",
  "basicInfo": {
    "name": "Amanda Gonzalez",
    "email": "amanda.gonzalez@yahoo.co.uk",
    "company": "Super Nelson FunZone",
    "website": "www.supernelsonfunzone.co.uk",
    "country": "GB",
    "countryName": "United Kingdom",
    "timezone": "Europe/London",
    "language": "en",
    "phone": "+648067274729",
    "position": "Procurement Officer",
    "linkedIn": ""
  },
  "businessProfile": {
    "clientLevel": "C",
    "industry": "Specialty Store",
    "purchaseCategory": [
      "outdoor",
      "rc-toys",
      "infant-toddler"
    ],
    "estimatedVolume": "small",
    "companySize": "1000+",
    "annualRevenue": "$<100K",
    "firstContactExhibition": "Bangkok Toys & Games Fair",
    "firstContactYear": 2024,
    "lastContactDate": "2026-05-07",
    "status": "active",
    "preferredContactTime": "13:00",
    "notes": ""
  },
  "communicationHistory": {
    "totalEmailsSent": 16,
    "totalRepliesReceived": 8,
    "lastReplyDate": null,
    "replyRate": 50,
    "lastReplyIntent": null
  },
  "aiInsights": {
    "bestSendingDay": "Tuesday",
    "optimalTime": "16:00",
    "responsePattern": "considerate",
    "interestProducts": [
      "outdoor",
      "rc-toys"
    ],
    "stylePreference": "friendly",
    "lastDistillMatchScore": 0,
    "engagementScore": 64,
    "priorityScore": 50
  },
  "tags": [],
  "metadata": {
    "createdAt": "2022-12-17T14:32:53.542Z",
    "updatedAt": "2026-05-09T14:32:53.542Z",
    "version": 1,
    "dataHash": "0741089076228920",
    "importSource": "system-initialization",
    "importBatch": "batch-001-2026-05-09"
  }
}