{
  "clientId": "CLT-06185",
  "emailAccount": "account-062",
  "basicInfo": {
    "name": "Ashley White",
    "email": "ashley.white@hotmail.com",
    "company": "Fantastic Rodriguez WonderToys",
    "website": "www.fantasticrodriguezwondertoys.es",
    "country": "ES",
    "countryName": "Spain",
    "timezone": "Europe/Madrid",
    "language": "es",
    "phone": "+6309215087751",
    "position": "Owner",
    "linkedIn": ""
  },
  "businessProfile": {
    "clientLevel": "C",
    "industry": "Import Export Company",
    "purchaseCategory": [
      "classic-toys"
    ],
    "estimatedVolume": "small",
    "companySize": "201-500",
    "annualRevenue": "$<100K",
    "firstContactExhibition": "New York Toy Fair",
    "firstContactYear": 2016,
    "lastContactDate": "2026-02-17",
    "status": "active",
    "preferredContactTime": "11:00",
    "notes": ""
  },
  "communicationHistory": {
    "totalEmailsSent": 2,
    "totalRepliesReceived": 8,
    "lastReplyDate": "2026-05-06",
    "replyRate": 400,
    "lastReplyIntent": null
  },
  "aiInsights": {
    "bestSendingDay": "Wednesday",
    "optimalTime": "12:00",
    "responsePattern": "considerate",
    "interestProducts": [
      "classic-toys"
    ],
    "stylePreference": "formal",
    "lastDistillMatchScore": 0,
    "engagementScore": 67,
    "priorityScore": 53
  },
  "tags": [],
  "metadata": {
    "createdAt": "2025-07-13T14:32:53.583Z",
    "updatedAt": "2026-05-09T14:32:53.583Z",
    "version": 1,
    "dataHash": "af3f4336679b16df",
    "importSource": "system-initialization",
    "importBatch": "batch-001-2026-05-09"
  }
}