{
  "clientId": "CLT-06385",
  "emailAccount": "account-064",
  "basicInfo": {
    "name": "Dorothy Garcia",
    "email": "dorothy.garcia@outlook.com",
    "company": "Premier Harris Imports",
    "website": "www.premierharrisimports.com",
    "country": "US",
    "countryName": "United States",
    "timezone": "America/New_York",
    "language": "en",
    "phone": "+3185336829955",
    "position": "Procurement Officer",
    "linkedIn": ""
  },
  "businessProfile": {
    "clientLevel": "B",
    "industry": "Department Store",
    "purchaseCategory": [
      "outdoor",
      "educational"
    ],
    "estimatedVolume": "medium",
    "companySize": "1-10",
    "annualRevenue": "$500K-$2M",
    "firstContactExhibition": "Hong Kong Toys & Games Fair",
    "firstContactYear": 2024,
    "lastContactDate": "2025-09-22",
    "status": "sleeping",
    "preferredContactTime": "11:00",
    "notes": ""
  },
  "communicationHistory": {
    "totalEmailsSent": 5,
    "totalRepliesReceived": 2,
    "lastReplyDate": null,
    "replyRate": 40,
    "lastReplyIntent": null
  },
  "aiInsights": {
    "bestSendingDay": "Wednesday",
    "optimalTime": "16:00",
    "responsePattern": null,
    "interestProducts": [
      "outdoor",
      "educational"
    ],
    "stylePreference": "professional",
    "lastDistillMatchScore": 0,
    "engagementScore": 22,
    "priorityScore": 89
  },
  "tags": [],
  "metadata": {
    "createdAt": "2026-03-07T14:32:53.640Z",
    "updatedAt": "2026-05-09T14:32:53.640Z",
    "version": 1,
    "dataHash": "124f84c1080d3720",
    "importSource": "system-initialization",
    "importBatch": "batch-001-2026-05-09"
  }
}