{
  "clientId": "CLT-07330",
  "emailAccount": "account-074",
  "basicInfo": {
    "name": "Eric Walker",
    "email": "eric.walker@gmail.com",
    "company": "Global Davis LLC",
    "website": "www.globaldavisllc.com",
    "country": "BE",
    "countryName": "Belgium",
    "timezone": "Europe/Brussels",
    "language": "en",
    "phone": "+3129965036677",
    "position": "Director",
    "linkedIn": ""
  },
  "businessProfile": {
    "clientLevel": "C",
    "industry": "Toy Retail Chain",
    "purchaseCategory": [
      "classic-toys",
      "infant-toddler"
    ],
    "estimatedVolume": "small",
    "companySize": "501-1000",
    "annualRevenue": "$500K-$2M",
    "firstContactExhibition": "Australian Toy Association Fair",
    "firstContactYear": 2021,
    "lastContactDate": "2025-02-13",
    "status": "churned",
    "preferredContactTime": "08:00",
    "notes": ""
  },
  "communicationHistory": {
    "totalEmailsSent": 9,
    "totalRepliesReceived": 2,
    "lastReplyDate": null,
    "replyRate": 22,
    "lastReplyIntent": null
  },
  "aiInsights": {
    "bestSendingDay": "Tuesday",
    "optimalTime": "13:00",
    "responsePattern": null,
    "interestProducts": [
      "classic-toys",
      "infant-toddler"
    ],
    "stylePreference": "professional",
    "lastDistillMatchScore": 0,
    "engagementScore": 8,
    "priorityScore": 55
  },
  "tags": [],
  "metadata": {
    "createdAt": "2024-01-01T14:32:53.917Z",
    "updatedAt": "2026-05-09T14:32:53.917Z",
    "version": 1,
    "dataHash": "e75d57f0729f3a49",
    "importSource": "system-initialization",
    "importBatch": "batch-001-2026-05-09"
  }
}