{
  "clientId": "CLT-04946",
  "emailAccount": "account-050",
  "basicInfo": {
    "name": "Andrew Brown",
    "email": "andrew.brown@company.com",
    "company": "Bright Flores Distribution",
    "website": "www.brightfloresdistribution.com",
    "country": "DK",
    "countryName": "Denmark",
    "timezone": "Europe/Copenhagen",
    "language": "en",
    "phone": "+8874289954137",
    "position": "Buyer",
    "linkedIn": ""
  },
  "businessProfile": {
    "clientLevel": "C",
    "industry": "Gift Shop Chain",
    "purchaseCategory": [
      "rc-toys",
      "educational"
    ],
    "estimatedVolume": "small",
    "companySize": "1-10",
    "annualRevenue": "$10M-$50M",
    "firstContactExhibition": "Mexico Toy Expo",
    "firstContactYear": 2015,
    "lastContactDate": "2026-05-03",
    "status": "active",
    "preferredContactTime": "11:00",
    "notes": ""
  },
  "communicationHistory": {
    "totalEmailsSent": 13,
    "totalRepliesReceived": 3,
    "lastReplyDate": "2026-04-23",
    "replyRate": 23,
    "lastReplyIntent": null
  },
  "aiInsights": {
    "bestSendingDay": "Wednesday",
    "optimalTime": "11:00",
    "responsePattern": "quick-responder",
    "interestProducts": [
      "rc-toys",
      "educational"
    ],
    "stylePreference": "friendly",
    "lastDistillMatchScore": 0,
    "engagementScore": 87,
    "priorityScore": 57
  },
  "tags": [],
  "metadata": {
    "createdAt": "2026-05-03T14:32:53.232Z",
    "updatedAt": "2026-05-09T14:32:53.232Z",
    "version": 1,
    "dataHash": "2ef47c03741fefc4",
    "importSource": "system-initialization",
    "importBatch": "batch-001-2026-05-09"
  }
}