{
  "clientId": "CLT-02407",
  "emailAccount": "account-025",
  "basicInfo": {
    "name": "Thomas Hill",
    "email": "thomas.hill@orange.fr",
    "company": "Premier Wilson DreamPlay",
    "website": "www.premierwilsondreamplay.fr",
    "country": "FR",
    "countryName": "France",
    "timezone": "Europe/Paris",
    "language": "fr",
    "phone": "+6696510093651",
    "position": "CEO",
    "linkedIn": ""
  },
  "businessProfile": {
    "clientLevel": "C",
    "industry": "Department Store",
    "purchaseCategory": [
      "infant-toddler",
      "outdoor",
      "classic-toys"
    ],
    "estimatedVolume": "small",
    "companySize": "201-500",
    "annualRevenue": "$500K-$2M",
    "firstContactExhibition": "Shanghai Toy Expo",
    "firstContactYear": 2015,
    "lastContactDate": "2025-05-25",
    "status": "churned",
    "preferredContactTime": "17:00",
    "notes": ""
  },
  "communicationHistory": {
    "totalEmailsSent": 1,
    "totalRepliesReceived": 2,
    "lastReplyDate": null,
    "replyRate": 200,
    "lastReplyIntent": null
  },
  "aiInsights": {
    "bestSendingDay": "Tuesday",
    "optimalTime": "10:00",
    "responsePattern": null,
    "interestProducts": [
      "infant-toddler",
      "outdoor"
    ],
    "stylePreference": "formal",
    "lastDistillMatchScore": 0,
    "engagementScore": 19,
    "priorityScore": 59
  },
  "tags": [],
  "metadata": {
    "createdAt": "2022-04-26T14:32:52.457Z",
    "updatedAt": "2026-05-09T14:32:52.457Z",
    "version": 1,
    "dataHash": "32fb9be120f1d1a4",
    "importSource": "system-initialization",
    "importBatch": "batch-001-2026-05-09"
  }
}