{
  "clientId": "CLT-02451",
  "emailAccount": "account-025",
  "basicInfo": {
    "name": "Nicholas Moore",
    "email": "nicholas.moore@yahoo.com",
    "company": "Joyful Wilson Group",
    "website": "www.joyfulwilsongroup.com",
    "country": "BR",
    "countryName": "Brazil",
    "timezone": "America/Sao_Paulo",
    "language": "en",
    "phone": "+5316514343368",
    "position": "Procurement Officer",
    "linkedIn": ""
  },
  "businessProfile": {
    "clientLevel": "B",
    "industry": "Toy Retail Chain",
    "purchaseCategory": [
      "rc-toys"
    ],
    "estimatedVolume": "medium",
    "companySize": "201-500",
    "annualRevenue": "$100K-$500K",
    "firstContactExhibition": "Moscow Toy Show",
    "firstContactYear": 2023,
    "lastContactDate": "2026-02-23",
    "status": "active",
    "preferredContactTime": "12:00",
    "notes": ""
  },
  "communicationHistory": {
    "totalEmailsSent": 4,
    "totalRepliesReceived": 4,
    "lastReplyDate": null,
    "replyRate": 100,
    "lastReplyIntent": null
  },
  "aiInsights": {
    "bestSendingDay": "Friday",
    "optimalTime": "15:00",
    "responsePattern": "considerate",
    "interestProducts": [
      "rc-toys"
    ],
    "stylePreference": "formal",
    "lastDistillMatchScore": 0,
    "engagementScore": 72,
    "priorityScore": 80
  },
  "tags": [],
  "metadata": {
    "createdAt": "2024-11-10T14:32:52.470Z",
    "updatedAt": "2026-05-09T14:32:52.470Z",
    "version": 1,
    "dataHash": "7ae481b288a457ca",
    "importSource": "system-initialization",
    "importBatch": "batch-001-2026-05-09"
  }
}